.gitignore
ML Pipeline Architecture.pdf
README.md
loaders.py
main.py
pyproject.toml
requirements.txt
setup.py
.github/workflows/python-publish.yml
.idea/misc.xml
.idea/mle_deacthlon.iml
.idea/modules.xml
.idea/vcs.xml
.idea/workspace.xml
.idea/inspectionProfiles/Project_Default.xml
.idea/inspectionProfiles/profiles_settings.xml
__pycache__/loaders.cpython-38.pyc
data/inputs/bu_feat.csv.gz
data/inputs/test.csv.gz
data/inputs/train.csv.gz
data/outputs/predictions.pkl
forecasting_mle_decathlon/__init__.py
forecasting_mle_decathlon.egg-info/PKG-INFO
forecasting_mle_decathlon.egg-info/SOURCES.txt
forecasting_mle_decathlon.egg-info/dependency_links.txt
forecasting_mle_decathlon.egg-info/requires.txt
forecasting_mle_decathlon.egg-info/top_level.txt
forecasting_mle_decathlon/__pycache__/__init__.cpython-38.pyc
forecasting_mle_decathlon/modeling/__init__.py
forecasting_mle_decathlon/modeling/modeling_pipeline.py
forecasting_mle_decathlon/modeling/prophet_estimator.py
forecasting_mle_decathlon/modeling/utils.py
forecasting_mle_decathlon/modeling/__pycache__/__init__.cpython-38.pyc
forecasting_mle_decathlon/modeling/__pycache__/modeling_pipeline.cpython-38.pyc
forecasting_mle_decathlon/modeling/__pycache__/prophet_estimator.cpython-38.pyc
forecasting_mle_decathlon/modeling/__pycache__/utils.cpython-38.pyc
forecasting_mle_decathlon/processing/__init__.py
forecasting_mle_decathlon/processing/data_transformer.py
forecasting_mle_decathlon/processing/processing.py
forecasting_mle_decathlon/processing/processing_pipeline.py
forecasting_mle_decathlon/processing/__pycache__/__init__.cpython-38.pyc
forecasting_mle_decathlon/processing/__pycache__/data_transformer.cpython-38.pyc
forecasting_mle_decathlon/processing/__pycache__/processing.cpython-38.pyc
forecasting_mle_decathlon/processing/__pycache__/processing_pipeline.cpython-38.pyc
modeling/__pycache__/__init__.cpython-38.pyc
modeling/__pycache__/modeling_pipeline.cpython-38.pyc
modeling/__pycache__/prophet_estimator.cpython-38.pyc
modeling/__pycache__/utils.cpython-38.pyc
notebooks/EDA.ipynb
notebooks/ForecastModel.ipynb
notebooks/ML-Pipeline.ipynb
processing/__pycache__/__init__.cpython-38.pyc
processing/__pycache__/data_transformer.cpython-38.pyc
