Metadata-Version: 1.0
Name: forecasting-mle-decathlon
Version: 0.1.2
Summary: Package to forecast sales
Home-page: UNKNOWN
Author: Rugery Pierrick
Author-email: rugery.pierrick@fake.com
License: UNKNOWN
Platform: UNKNOWN
